{
  "package" : {
    "name" : "com.MediaUp.MasterBuilder",
    "versionCode" : "18",
    "versionName" : "0.9.6.7",
    "platformBuildVersionName" : "11",
    "platformBuildVersionCode" : "30",
    "compileSdkVersion" : "30",
    "compileSdkVersionCodename" : "11"
  },
  "install-location" : "auto",
  "sdkVersion" : "26",
  "targetSdkVersion" : "30",
  "uses-permission" : {
    "name" : "android.permission.WRITE_SETTINGS"
  },
  "supports-gl-texture" : "GL_KHR_texture_compression_astc_ldr",
  "application-label" : "MasterBuilder",
  "application-label-af" : "MasterBuilder",
  "application-label-am" : "MasterBuilder",
  "application-label-ar" : "MasterBuilder",
  "application-label-az" : "MasterBuilder",
  "application-label-be" : "MasterBuilder",
  "application-label-bg" : "MasterBuilder",
  "application-label-bn" : "MasterBuilder",
  "application-label-bs" : "MasterBuilder",
  "application-label-ca" : "MasterBuilder",
  "application-label-cs" : "MasterBuilder",
  "application-label-da" : "MasterBuilder",
  "application-label-de" : "MasterBuilder",
  "application-label-el" : "MasterBuilder",
  "application-label-en" : "MasterBuilder",
  "application-label-en-AU" : "MasterBuilder",
  "application-label-en-GB" : "MasterBuilder",
  "application-label-en-IN" : "MasterBuilder",
  "application-label-es" : "MasterBuilder",
  "application-label-es-US" : "MasterBuilder",
  "application-label-et" : "MasterBuilder",
  "application-label-eu" : "MasterBuilder",
  "application-label-fa" : "MasterBuilder",
  "application-label-fi" : "MasterBuilder",
  "application-label-fr" : "MasterBuilder",
  "application-label-fr-CA" : "MasterBuilder",
  "application-label-gl" : "MasterBuilder",
  "application-label-gu" : "MasterBuilder",
  "application-label-hi" : "MasterBuilder",
  "application-label-hr" : "MasterBuilder",
  "application-label-hu" : "MasterBuilder",
  "application-label-hy" : "MasterBuilder",
  "application-label-in" : "MasterBuilder",
  "application-label-is" : "MasterBuilder",
  "application-label-it" : "MasterBuilder",
  "application-label-iw" : "MasterBuilder",
  "application-label-ja" : "MasterBuilder",
  "application-label-ka" : "MasterBuilder",
  "application-label-kk" : "MasterBuilder",
  "application-label-km" : "MasterBuilder",
  "application-label-kn" : "MasterBuilder",
  "application-label-ko" : "MasterBuilder",
  "application-label-ky" : "MasterBuilder",
  "application-label-lo" : "MasterBuilder",
  "application-label-lt" : "MasterBuilder",
  "application-label-lv" : "MasterBuilder",
  "application-label-mk" : "MasterBuilder",
  "application-label-ml" : "MasterBuilder",
  "application-label-mn" : "MasterBuilder",
  "application-label-mr" : "MasterBuilder",
  "application-label-ms" : "MasterBuilder",
  "application-label-my" : "MasterBuilder",
  "application-label-nb" : "MasterBuilder",
  "application-label-ne" : "MasterBuilder",
  "application-label-nl" : "MasterBuilder",
  "application-label-pa" : "MasterBuilder",
  "application-label-pl" : "MasterBuilder",
  "application-label-pt" : "MasterBuilder",
  "application-label-pt-BR" : "MasterBuilder",
  "application-label-pt-PT" : "MasterBuilder",
  "application-label-ro" : "MasterBuilder",
  "application-label-ru" : "MasterBuilder",
  "application-label-si" : "MasterBuilder",
  "application-label-sk" : "MasterBuilder",
  "application-label-sl" : "MasterBuilder",
  "application-label-sq" : "MasterBuilder",
  "application-label-sr" : "MasterBuilder",
  "application-label-sr-Latn" : "MasterBuilder",
  "application-label-sv" : "MasterBuilder",
  "application-label-sw" : "MasterBuilder",
  "application-label-ta" : "MasterBuilder",
  "application-label-te" : "MasterBuilder",
  "application-label-th" : "MasterBuilder",
  "application-label-tl" : "MasterBuilder",
  "application-label-tr" : "MasterBuilder",
  "application-label-uk" : "MasterBuilder",
  "application-label-ur" : "MasterBuilder",
  "application-label-uz" : "MasterBuilder",
  "application-label-vi" : "MasterBuilder",
  "application-label-zh" : "建筑大师",
  "application-label-zh-CN" : "建筑大师",
  "application-label-zh-HK" : "MasterBuilder",
  "application-label-zh-TW" : "MasterBuilder",
  "application-label-zu" : "MasterBuilder",
  "application-icon-120" : "res/mipmap-anydpi-v26/app_icon.xml",
  "application-icon-160" : "res/mipmap-anydpi-v26/app_icon.xml",
  "application-icon-240" : "res/mipmap-anydpi-v26/app_icon.xml",
  "application-icon-320" : "res/mipmap-anydpi-v26/app_icon.xml",
  "application-icon-480" : "res/mipmap-anydpi-v26/app_icon.xml",
  "application-icon-640" : "res/mipmap-anydpi-v26/app_icon.xml",
  "application-icon-65534" : "res/mipmap-anydpi-v26/app_icon.xml",
  "application" : {
    "label" : "MasterBuilder"
  },
  "launchable-activity" : {
    "name" : "com.unity3d.player.UnityPlayerActivity"
  },
  "feature-group" : "abel='",
  "uses-gl-es" : "0x30000",
  "uses-feature-not-required" : {
    "name" : "android.hardware.touchscreen.multitouch.distinct"
  },
  "uses-feature" : {
    "name" : "android.hardware.wifi"
  },
  "uses-implied-feature" : {
    "name" : "android.hardware.wifi"
  },
  "supports-screens" : "small' 'normal' 'large' 'xlarge",
  "supports-any-density" : "true",
  "locales" : "--_--' 'af' 'am' 'ar' 'az' 'be' 'bg' 'bn' 'bs' 'ca' 'cs' 'da' 'de' 'el' 'en' 'en-AU' 'en-GB' 'en-IN' 'es' 'es-US' 'et' 'eu' 'fa' 'fi' 'fr' 'fr-CA' 'gl' 'gu' 'hi' 'hr' 'hu' 'hy' 'in' 'is' 'it' 'iw' 'ja' 'ka' 'kk' 'km' 'kn' 'ko' 'ky' 'lo' 'lt' 'lv' 'mk' 'ml' 'mn' 'mr' 'ms' 'my' 'nb' 'ne' 'nl' 'pa' 'pl' 'pt' 'pt-BR' 'pt-PT' 'ro' 'ru' 'si' 'sk' 'sl' 'sq' 'sr' 'sr-Latn' 'sv' 'sw' 'ta' 'te' 'th' 'tl' 'tr' 'uk' 'ur' 'uz' 'vi' 'zh' 'zh-CN' 'zh-HK' 'zh-TW' 'zu",
  "densities" : "120' '160' '240' '320' '480' '640' '65534",
  "native-code" : "armeabi-v7a",
  "extractor" : {
    "meta" : {
      "timestamp" : 1684602053
    },
    "icons" : {
    }
  }
}